notebook_error_reporter/__init__.py
notebook_error_reporter/error_event/__init__.py
notebook_error_reporter/error_event/_traceback.py
notebook_error_reporter/error_event/error_event.py
notebook_error_reporter/error_event/error_message.py
notebook_error_reporter/error_event/error_store.py
notebook_error_reporter/serverside/__init__.py
notebook_error_reporter/serverside/crud.py
notebook_error_reporter/serverside/database.py
notebook_error_reporter/serverside/models.py
notebook_error_reporter/serverside/routes.py
notebook_error_reporter/serverside/schemas.py
notebook_error_reporter-0.1.dist-info/LICENSE
notebook_error_reporter-0.1.dist-info/METADATA
notebook_error_reporter-0.1.dist-info/WHEEL
notebook_error_reporter-0.1.dist-info/top_level.txt
notebook_error_reporter-0.1.dist-info/RECORD
