Metadata-Version: 2.1
Name: notebook-error-reporter
Version: 0.1
Summary: A error notification system for remote Jupyter notebooks
Home-page: https://github.com/matteoferla/remote-notebook-error-collection
Author: Matteo Ferla
Author-email: matteo.ferla@gmail.com
License: MIT
Platform: UNKNOWN
Classifier: Development Status :: 3 - Alpha
Classifier: Intended Audience :: Science/Research
Classifier: Topic :: Scientific/Engineering :: Bio-Informatics
Classifier: Topic :: Scientific/Engineering :: Chemistry
Classifier: License :: OSI Approved :: MIT License
Classifier: Programming Language :: Python :: 3.7
Classifier: Programming Language :: Python :: 3.8
Classifier: Programming Language :: Python :: 3.9
Requires-Python: >=3.7
License-File: LICENSE
Requires-Dist: requests
Provides-Extra: server
Requires-Dist: uvicorn ; extra == 'server'
Requires-Dist: fastapi ; extra == 'server'
Requires-Dist: databases ; extra == 'server'
Requires-Dist: pydantic ; extra == 'server'
Requires-Dist: sqlalchemy ; extra == 'server'
